README.rst
setup.py
jsonrpcake/__init__.py
jsonrpcake/__main__.py
jsonrpcake/cli.py
jsonrpcake/compat.py
jsonrpcake/core.py
jsonrpcake/input.py
jsonrpcake/models.py
jsonrpcake/output.py
jsonrpcake/solarized.py
jsonrpcake/utils.py
jsonrpcake.egg-info/PKG-INFO
jsonrpcake.egg-info/SOURCES.txt
jsonrpcake.egg-info/dependency_links.txt
jsonrpcake.egg-info/entry_points.txt
jsonrpcake.egg-info/requires.txt
jsonrpcake.egg-info/top_level.txt