Metadata-Version: 1.0
Name: jsonrpcake
Version: 1.0.0
Summary: JSONRPCake - a CLI JSON-RPC client for humans.
Home-page: UNKNOWN
Author: Joe Hillenbrand
Author-email: joehillen@gmail.com
License: BSD
Platform: UNKNOWN
